{"storage_stack": {"fstyp": "xfs", "mount_dax": true, "blockdev_stack": {"identity": "devpmem"}}, "result": {"_asdict": {"identity": "filebench-oltp", "workload": "oltp", "vars": {"ndbwriters": [1, 2, 3, 4, 5, 6, 7, 8, 9, 10, 11, 12, 13, 14, 15, 16]}}, "identity": "filebench-oltp", "config": {"filebench_binary": "/usr/local/bin/filebench", "name": "oltp", "dir": "/dut_linux_fs/2", "runtime_secs": 10, "vars": {"ndbwriters": 10}}, "result": {"stdout": "Filebench Version 1.5-alpha3\n0.000: Allocated 177MB of shared memory\n0.001: OLTP Version 3.0  personality successfully loaded\n0.001: Populating and pre-allocating filesets\n0.001: logfile populated: 1 files, avg. dir. width = 1024, avg. dir. depth = 0.0, 0 leafdirs, 10.000MB total size\n0.001: Reusing existing logfile tree\n0.001: Pre-allocating files in logfile tree\n0.001: datafiles populated: 10 files, avg. dir. width = 1024, avg. dir. depth = 0.3, 0 leafdirs, 100.000MB total size\n0.001: Reusing existing datafiles tree\n0.001: Pre-allocating files in datafiles tree\n0.001: Waiting for pre-allocation to finish (in case of a parallel pre-allocation)\n0.001: Population and pre-allocation of filesets completed\n0.001: Starting 200 shadow instances\n0.033: Starting 10 dbwr instances\n0.035: Starting 1 lgwr instances\n1.036: Running...\n11.040: Run took 10 seconds...\n11.047: Per-Operation Breakdown\nrandom-rate          0ops        0ops/s   0.0mb/s    0.000ms/op [0.000ms - 0.000ms]\nshadow-post-dbwr     705082ops    70488ops/s   0.0mb/s    0.039ms/op [0.002ms - 51.442ms]\nshadow-post-lg       705082ops    70488ops/s   0.0mb/s    0.003ms/op [0.000ms - 13.971ms]\nshadowhog            705093ops    70489ops/s   0.0mb/s    0.130ms/op [0.060ms - 26.194ms]\nshadowread           730797ops    73059ops/s 137.7mb/s    2.221ms/op [0.001ms - 235.949ms]\ndbwr-aiowait         7050ops      705ops/s   0.0mb/s    0.025ms/op [0.002ms - 9.550ms]\ndbwr-block           7050ops      705ops/s   0.0mb/s   13.154ms/op [0.001ms - 79.183ms]\ndbwr-hog             7059ops      706ops/s   0.0mb/s    0.006ms/op [0.003ms - 0.620ms]\ndbwrite-a            707192ops    70699ops/s 137.8mb/s    0.008ms/op [0.000ms - 40.542ms]\nlg-block             220ops       22ops/s   0.0mb/s   45.141ms/op [35.694ms - 229.243ms]\nlg-aiowait           221ops       22ops/s   0.0mb/s    0.000ms/op [0.000ms - 0.002ms]\nlg-write             222ops       22ops/s   5.5mb/s    0.005ms/op [0.002ms - 0.084ms]\n11.047: IO Summary: 1445482 ops 144506.452 ops/s 73059/70721 rd/wr 281.1mb/s 1.127ms/op\n11.047: Shutting down processes\n", "stderr": "", "metrics": {"summary_ops": 1445482, "summary_ops_per_sec": 144506.452}}}}