{"storage_stack": {"fstyp": "xfs", "mount_dax": false, "blockdev_stack": {"identity": "dm-writecache"}}, "result": {"identity": "mariadb-sysbench-oltp_insert", "config": {"dir": "/dut_linux_fs/0", "mariadb": {"docker_image": {"repository": "mariadb", "tag": "10.5.9"}}, "sysbench_checkout": "/root/src/sysbench", "threads": 3, "runtime_secs": 10}, "result": {"stdout": "sysbench 1.0.20-ebf1c90 (using bundled LuaJIT 2.1.0-beta2)\n\nRunning the test with following options:\nNumber of threads: 3\nInitializing random number generator from current time\n\n\nInitializing worker threads...\n\nThreads started!\n\nSQL statistics:\n    queries performed:\n        read:                            0\n        write:                           211880\n        other:                           0\n        total:                           211880\n    transactions:                        211880 (21182.02 per sec.)\n    queries:                             211880 (21182.02 per sec.)\n    ignored errors:                      0      (0.00 per sec.)\n    reconnects:                          0      (0.00 per sec.)\n\nGeneral statistics:\n    total time:                          10.0007s\n    total number of events:              211880\n\nLatency (ms):\n         min:                                    0.07\n         avg:                                    0.14\n         max:                                   79.85\n         95th percentile:                        0.21\n         sum:                                29542.02\n\nThreads fairness:\n    events (avg/stddev):           70626.6667/101.69\n    execution time (avg/stddev):   9.8473/0.00\n\n", "stderr": "", "runtime_secs": 10.017017312347889, "metrics": {"Running the test with following options": {"Number of threads": 3.0}, "SQL statistics": {"read": 0.0, "write": 211880.0, "other": 0.0, "total": 211880.0, "transactions_total": 211880.0, "transactions_per_sec": 21182.02, "queries_total": 211880.0, "queries_per_sec": 21182.02, "ignored errors_total": 0.0, "ignored errors_per_sec": 0.0, "reconnects_total": 0.0, "reconnects_per_sec": 0.0}, "General statistics": {"total time": 10.0007, "total number of events": 211880.0}, "Latency (ms)": {"min": 0.07, "avg": 0.14, "max": 79.85, "95th percentile": 0.21, "sum": 29542.02}, "Threads fairness": {"events (avg/stddev)": 70626.6667, "execution time (avg/stddev)": 9.8473}}}}}