{"storage_stack": {"fstyp": "ext4", "mount_dax": true, "blockdev_stack": {"identity": "devpmem"}}, "result": {"_asdict": {"identity": "filebench-varmail", "workload": "varmail", "vars": {"nthreads": [1, 2, 3, 4, 5, 6, 7, 8, 9, 10, 11, 12, 13, 14, 15, 16]}}, "identity": "filebench-varmail", "config": {"filebench_binary": "/usr/local/bin/filebench", "name": "varmail", "dir": "/dut_linux_fs/1", "runtime_secs": 10, "vars": {"nthreads": 14}}, "result": {"stdout": "Filebench Version 1.5-alpha3\n0.000: Allocated 177MB of shared memory\n0.001: Varmail Version 3.0 personality successfully loaded\n0.001: Populating and pre-allocating filesets\n0.002: bigfileset populated: 1000 files, avg. dir. width = 1000000, avg. dir. depth = 0.5, 0 leafdirs, 14.959MB total size\n0.002: Removing bigfileset tree (if exists)\n0.016: Pre-allocating directories in bigfileset tree\n0.016: Pre-allocating files in bigfileset tree\n0.042: Waiting for pre-allocation to finish (in case of a parallel pre-allocation)\n0.042: Population and pre-allocation of filesets completed\n0.043: Starting 1 filereader instances\n1.045: Running...\n11.046: Run took 10 seconds...\n11.046: Per-Operation Breakdown\nclosefile4           174814ops    17480ops/s   0.0mb/s    0.001ms/op [0.000ms - 0.088ms]\nreadfile4            174814ops    17480ops/s 271.8mb/s    0.024ms/op [0.002ms - 0.375ms]\nopenfile4            174814ops    17480ops/s   0.0mb/s    0.004ms/op [0.001ms - 0.091ms]\nclosefile3           174814ops    17480ops/s   0.0mb/s    0.001ms/op [0.000ms - 0.055ms]\nfsyncfile3           174815ops    17480ops/s   0.0mb/s    0.208ms/op [0.002ms - 8.115ms]\nappendfilerand3      174818ops    17481ops/s 136.6mb/s    0.058ms/op [0.004ms - 0.300ms]\nreadfile3            174818ops    17481ops/s 271.6mb/s    0.024ms/op [0.002ms - 0.197ms]\nopenfile3            174818ops    17481ops/s   0.0mb/s    0.004ms/op [0.002ms - 0.752ms]\nclosefile2           174818ops    17481ops/s   0.0mb/s    0.001ms/op [0.000ms - 0.064ms]\nfsyncfile2           174821ops    17481ops/s   0.0mb/s    0.216ms/op [0.046ms - 2.410ms]\nappendfilerand2      174825ops    17481ops/s 136.7mb/s    0.043ms/op [0.009ms - 0.280ms]\ncreatefile2          174825ops    17481ops/s   0.0mb/s    0.070ms/op [0.008ms - 0.528ms]\ndeletefile1          174828ops    17482ops/s   0.0mb/s    0.124ms/op [0.013ms - 0.561ms]\n11.046: IO Summary: 2272642 ops 227250.020 ops/s 34961/34962 rd/wr 816.7mb/s 0.060ms/op\n11.046: Shutting down processes\n", "stderr": "", "metrics": {"summary_ops": 2272642, "summary_ops_per_sec": 227250.02}}}}