{"storage_stack": {"fstyp": "ext4", "mount_dax": true, "blockdev_stack": {"identity": "devpmem"}}, "result": {"identity": "redis-SET", "config": {"redis6_checkout": "/root/src/redis", "dir": "/dut_linux_fs/5", "nrequests": {"type": "fixed", "nrequests": 1000000}, "keyspacelen": "nrequests", "pipeline_numreq": 1, "datasize": 3, "clients": 7, "threads": 7}, "result": {"estimate": null, "main": {"stdout": "\"test\",\"rps\",\"avg_latency_ms\",\"min_latency_ms\",\"p50_latency_ms\",\"p95_latency_ms\",\"p99_latency_ms\",\"max_latency_ms\"\n\"SET\",\"36360.99\",\"0.182\",\"0.032\",\"0.183\",\"0.279\",\"0.319\",\"3.399\"\n", "metrics": {"rps": 36360.99, "avg_latency_ms": 0.182, "min_latency_ms": 0.032, "p50_latency_ms": 0.183, "p95_latency_ms": 0.279, "p99_latency_ms": 0.319, "max_latency_ms": 3.399}, "runtime_secs": 27.50974849704653, "nrequests": 1000000, "keyspacelen": 1000000}}}}