{"store": {"zil_pmem_builddir": ["/home/schwarz/zil-pmem/zil-pmem"], "fio_binary": ["/usr/bin/fio"], "devdax": ["/dev/dax0.0"], "fsdax": ["/dev/pmem0.2"], "blockdevice": ["/dev/pmem2", "/dev/pmem3", "/dev/pmem4"]}, "pmem_setup_data": {"interleaving": 4, "pmem_config_snippet": {"PersistentMemoryType": "AppDirect", "SocketID": "0x0000", "DimmID": "0x0001, 0x0011, 0x0101, 0x0111"}, "pmem_config": {"regions": [{"PersistentMemoryType": "AppDirect", "SocketID": "0x0000", "DimmID": "0x0001, 0x0011, 0x0101, 0x0111", "namespaces": [{"mode": "devdax", "size": 10737418240, "configlabel": "devdax"}, {"mode": "fsdax", "size": 10737418240, "configlabel": "fsdax"}]}, {"PersistentMemoryType": "AppDirectNotInterleaved", "SocketID": "0x0001", "DimmID": "0x1011", "namespaces": [{"mode": "fsdax", "size": 107374182400, "configlabel": "blockdevice"}]}, {"PersistentMemoryType": "AppDirectNotInterleaved", "SocketID": "0x0001", "DimmID": "0x1101", "namespaces": [{"mode": "fsdax", "size": 107374182400, "configlabel": "blockdevice"}]}, {"PersistentMemoryType": "AppDirectNotInterleaved", "SocketID": "0x0001", "DimmID": "0x1111", "namespaces": [{"mode": "fsdax", "size": 107374182400, "configlabel": "blockdevice"}]}]}}, "isolcpus_data": {"possible_cpus": "{0, 1, 2, 3, 4, 5, 6, 7, 8, 9, 10, 11, 12, 13, 14, 15, 16, 17, 18, 19, 20, 21, 22, 23, 24, 25, 26, 27, 28, 29, 30, 31, 32, 33, 34, 35, 36, 37, 38, 39, 40, 41, 42, 43, 44, 45, 46, 47, 48, 49, 50, 51, 52, 53, 54, 55, 56, 57, 58, 59, 60, 61, 62, 63, 64, 65, 66, 67, 68, 69, 70, 71}", "isolated_cpus": "{18, 19, 20, 21, 22, 23, 24, 25, 26, 27, 28, 29, 30, 31, 32, 33, 34, 35, 54, 55, 56, 57, 58, 59, 60, 61, 62, 63, 64, 65, 66, 67, 68, 69, 70, 71}", "node_cpus": "{0, 1, 2, 3, 4, 5, 6, 7, 8, 9, 10, 11, 12, 13, 14, 15, 16, 17, 36, 37, 38, 39, 40, 41, 42, 43, 44, 45, 46, 47, 48, 49, 50, 51, 52, 53}", "node_number": 0, "node_path": "/sys/devices/system/node/node0/cpulist"}, "identity": "fio-4k-sync-rand-write--size-div-by-numjobs", "fio_config": {"fio_binary": "/usr/bin/fio", "blocksize": 4096, "runtime_seconds": 10, "ramp_seconds": 2, "fsync_every": 0, "numjobs": 23, "sync": 1, "size": 46684427, "target": {"type": "fs", "filename_format_str": "/dut/ds{}/fio_jobfile", "require_filename_format_str_parent_is_mountpoint": true, "prewrite_mode": "delete"}}, "fio_jsonplus": {"fio version": "fio-3.21", "timestamp": 1620559187, "timestamp_ms": 1620559187205, "time": "Sun May  9 13:19:47 2021", "jobs": [{"jobname": "run_fio_benchmark", "groupid": 0, "error": 0, "eta": 0, "elapsed": 13, "job options": {"name": "run_fio_benchmark", "ioengine": "sync", "end_fsync": "1", "size": "46684427", "bs": "4096", "rw": "randwrite", "time_based": "1", "runtime": "10", "ramp_time": "2", "sync": "1", "direct": "0", "fsync": "0", "numjobs": "23", "group_reporting": "1", "filename_format": "/dut/ds$jobnum/fio_jobfile"}, "read": {"io_bytes": 0, "io_kbytes": 0, "bw_bytes": 0, "bw": 0, "iops": 0.0, "runtime": 0, "total_ios": 0, "short_ios": 0, "drop_ios": 0, "slat_ns": {"min": 0, "max": 0, "mean": 0.0, "stddev": 0.0, "N": 0}, "clat_ns": {"min": 0, "max": 0, "mean": 0.0, "stddev": 0.0, "N": 0}, "lat_ns": {"min": 0, "max": 0, "mean": 0.0, "stddev": 0.0, "N": 0}, "bw_min": 0, "bw_max": 0, "bw_agg": 0.0, "bw_mean": 0.0, "bw_dev": 0.0, "bw_samples": 0, "iops_min": 0, "iops_max": 0, "iops_mean": 0.0, "iops_stddev": 0.0, "iops_samples": 0}, "write": {"io_bytes": 26589188096, "io_kbytes": 25966004, "bw_bytes": 2658387132, "bw": 2596081, "iops": 649020.295941, "runtime": 10002, "total_ios": 6491501, "short_ios": 0, "drop_ios": 0, "slat_ns": {"min": 0, "max": 0, "mean": 0.0, "stddev": 0.0, "N": 0}, "clat_ns": {"min": 8251, "max": 929474312, "mean": 34250.053301, "stddev": 2151136.823026, "N": 6491501, "percentile": {"1.000000": 11456, "5.000000": 13888, "10.000000": 15424, "20.000000": 18048, "30.000000": 19840, "40.000000": 21632, "50.000000": 23680, "60.000000": 25728, "70.000000": 28544, "80.000000": 33024, "90.000000": 41216, "95.000000": 48896, "99.000000": 70144, "99.500000": 85504, "99.900000": 123392, "99.950000": 154624, "99.990000": 358400}, "bins": {"8256": 1, "9024": 3, "9152": 16, "9280": 31, "9408": 79, "9536": 189, "9664": 435, "9792": 841, "9920": 1494, "10048": 2418, "10176": 3370, "10304": 4400, "10432": 5212, "10560": 5855, "10688": 6430, "10816": 6656, "10944": 6632, "11072": 6486, "11200": 6075, "11328": 5930, "11456": 5646, "11584": 5457, "11712": 5356, "11840": 5635, "11968": 5604, "12096": 6117, "12224": 6688, "12352": 7563, "12480": 8756, "12608": 10158, "12736": 11782, "12864": 13425, "12992": 15235, "13120": 17348, "13248": 18914, "13376": 20725, "13504": 22636, "13632": 24027, "13760": 25634, "13888": 26918, "14016": 27928, "14144": 28740, "14272": 28922, "14400": 29111, "14528": 28592, "14656": 28602, "14784": 28174, "14912": 27550, "15040": 27028, "15168": 26821, "15296": 25989, "15424": 25642, "15552": 25471, "15680": 25253, "15808": 25040, "15936": 25135, "16064": 25288, "16192": 25965, "16320": 26220, "16512": 54787, "16768": 58407, "17024": 62222, "17280": 66939, "17536": 71087, "17792": 76213, "18048": 81375, "18304": 85303, "18560": 89800, "18816": 93614, "19072": 96496, "19328": 98800, "19584": 100576, "19840": 101214, "20096": 100859, "20352": 100401, "20608": 99240, "20864": 97242, "21120": 95615, "21376": 93814, "21632": 90828, "21888": 89770, "22144": 87685, "22400": 85484, "22656": 83407, "22912": 82626, "23168": 80952, "23424": 79302, "23680": 78739, "23936": 76706, "24192": 76152, "24448": 75515, "24704": 74199, "24960": 72763, "25216": 71535, "25472": 70594, "25728": 68574, "25984": 67081, "26240": 65998, "26496": 63928, "26752": 62064, "27008": 60072, "27264": 58453, "27520": 56154, "27776": 54256, "28032": 52498, "28288": 50391, "28544": 48464, "28800": 47199, "29056": 45259, "29312": 43677, "29568": 42099, "29824": 41080, "30080": 39983, "30336": 38589, "30592": 37560, "30848": 36477, "31104": 35575, "31360": 34367, "31616": 33832, "31872": 33215, "32128": 32081, "32384": 31657, "32640": 31111, "33024": 59292, "33536": 56592, "34048": 53835, "34560": 51395, "35072": 49063, "35584": 47396, "36096": 45377, "36608": 43022, "37120": 41348, "37632": 39248, "38144": 38174, "38656": 35936, "39168": 35068, "39680": 32932, "40192": 31363, "40704": 30462, "41216": 28862, "41728": 27519, "42240": 26319, "42752": 24967, "43264": 24227, "43776": 22972, "44288": 21840, "44800": 20778, "45312": 20082, "45824": 19242, "46336": 18684, "46848": 17671, "47360": 17020, "47872": 16509, "48384": 15988, "48896": 15112, "49408": 14562, "49920": 14031, "50432": 13449, "50944": 12689, "51456": 12056, "51968": 11730, "52480": 11028, "52992": 10549, "53504": 9866, "54016": 9627, "54528": 8962, "55040": 8576, "55552": 7968, "56064": 7740, "56576": 7087, "57088": 6724, "57600": 6410, "58112": 6074, "58624": 5563, "59136": 5338, "59648": 4943, "60160": 4672, "60672": 4340, "61184": 4150, "61696": 3760, "62208": 3621, "62720": 3324, "63232": 3166, "63744": 2865, "64256": 2740, "64768": 2604, "65280": 2512, "66048": 4451, "67072": 3896, "68096": 3527, "69120": 3251, "70144": 2928, "71168": 2631, "72192": 2515, "73216": 2465, "74240": 2341, "75264": 2181, "76288": 2143, "77312": 2113, "78336": 2030, "79360": 2005, "80384": 1995, "81408": 1891, "82432": 1875, "83456": 1814, "84480": 1719, "85504": 1722, "86528": 1617, "87552": 1637, "88576": 1462, "89600": 1482, "90624": 1427, "91648": 1354, "92672": 1195, "93696": 1151, "94720": 1067, "95744": 971, "96768": 920, "97792": 833, "98816": 760, "99840": 761, "100864": 650, "101888": 660, "102912": 595, "103936": 541, "104960": 508, "105984": 462, "107008": 449, "108032": 403, "109056": 398, "110080": 384, "111104": 357, "112128": 319, "113152": 279, "114176": 304, "115200": 281, "116224": 253, "117248": 238, "118272": 269, "119296": 186, "120320": 191, "121344": 208, "122368": 201, "123392": 197, "124416": 171, "125440": 173, "126464": 160, "127488": 159, "128512": 146, "129536": 130, "130560": 134, "132096": 275, "134144": 234, "136192": 225, "138240": 215, "140288": 155, "142336": 181, "144384": 173, "146432": 148, "148480": 150, "150528": 168, "152576": 137, "154624": 131, "156672": 135, "158720": 132, "160768": 126, "162816": 124, "164864": 107, "166912": 96, "168960": 98, "171008": 103, "173056": 77, "175104": 67, "177152": 78, "179200": 81, "181248": 67, "183296": 58, "185344": 57, "187392": 42, "189440": 61, "191488": 45, "193536": 58, "195584": 44, "197632": 34, "199680": 33, "201728": 27, "203776": 43, "205824": 26, "207872": 33, "209920": 30, "211968": 28, "214016": 34, "216064": 31, "218112": 25, "220160": 18, "222208": 21, "224256": 21, "226304": 14, "228352": 11, "230400": 14, "232448": 11, "234496": 10, "236544": 7, "238592": 14, "240640": 8, "242688": 4, "244736": 11, "246784": 13, "248832": 15, "250880": 11, "252928": 8, "254976": 21, "257024": 17, "259072": 12, "261120": 11, "264192": 8, "268288": 14, "272384": 18, "276480": 6, "280576": 16, "284672": 14, "288768": 12, "292864": 12, "296960": 15, "301056": 5, "305152": 7, "309248": 7, "313344": 5, "317440": 9, "321536": 5, "325632": 7, "329728": 15, "333824": 11, "337920": 8, "342016": 10, "346112": 10, "350208": 7, "354304": 3, "358400": 9, "362496": 6, "366592": 6, "370688": 3, "374784": 3, "378880": 4, "382976": 5, "387072": 1, "391168": 3, "395264": 5, "399360": 3, "403456": 7, "407552": 4, "411648": 3, "415744": 7, "419840": 3, "423936": 4, "428032": 5, "432128": 2, "436224": 1, "440320": 2, "444416": 3, "448512": 1, "452608": 2, "460800": 2, "468992": 5, "473088": 2, "477184": 1, "481280": 1, "485376": 2, "493568": 1, "505856": 2, "518144": 1, "522240": 2, "528384": 4, "536576": 1, "544768": 2, "552960": 1, "561152": 2, "569344": 3, "577536": 1, "585728": 1, "602112": 1, "610304": 3, "618496": 5, "634880": 1, "643072": 4, "651264": 3, "659456": 3, "667648": 3, "675840": 2, "684032": 1, "708608": 1, "716800": 3, "741376": 3, "749568": 1, "757760": 4, "765952": 1, "774144": 3, "782336": 1, "790528": 1, "798720": 1, "806912": 1, "815104": 3, "823296": 5, "831488": 2, "839680": 1, "847872": 3, "856064": 1, "864256": 3, "872448": 2, "880640": 1, "888832": 1, "905216": 6, "913408": 1, "921600": 1, "937984": 2, "946176": 2, "954368": 1, "962560": 1, "970752": 1, "978944": 1, "987136": 6, "995328": 2, "1003520": 3, "1011712": 4, "1019904": 2, "1028096": 1, "1036288": 2, "1044480": 4, "1056768": 11, "1073152": 8, "1089536": 7, "1105920": 2, "1122304": 3, "1138688": 1, "1171456": 3, "1187840": 3, "1204224": 2, "1220608": 1, "1236992": 5, "1253376": 2, "1269760": 2, "1286144": 1, "1302528": 2, "1318912": 3, "1335296": 4, "1368064": 2, "1384448": 3, "1400832": 2, "1417216": 1, "1433600": 1, "1449984": 1, "1466368": 3, "1482752": 1, "1499136": 3, "1515520": 3, "1548288": 2, "1564672": 2, "1597440": 1, "1613824": 3, "1630208": 1, "1646592": 2, "1662976": 1, "1679360": 1, "1712128": 1, "1728512": 1, "1744896": 1, "1777664": 2, "1794048": 4, "1810432": 1, "1826816": 2, "1859584": 1, "1875968": 1, "1925120": 2, "1941504": 3, "1957888": 1, "2007040": 2, "2023424": 1, "2039808": 3, "2056192": 5, "2072576": 2, "2088960": 2, "2113536": 5, "2146304": 3, "2179072": 2, "2211840": 1, "2244608": 2, "2277376": 2, "2310144": 1, "2342912": 4, "2375680": 1, "2441216": 2, "2473984": 3, "2506752": 2, "2539520": 1, "2605056": 2, "2637824": 1, "2736128": 2, "2768896": 1, "2801664": 1, "2834432": 3, "2867200": 4, "2899968": 3, "2932736": 2, "2965504": 2, "3031040": 2, "3063808": 5, "3096576": 4, "3129344": 2, "3162112": 1, "3227648": 2, "3260416": 1, "3293184": 2, "3325952": 1, "3358720": 1, "3391488": 1, "3424256": 1, "3457024": 2, "3588096": 2, "3620864": 2, "3653632": 1, "3686400": 2, "3784704": 1, "3817472": 1, "3850240": 2, "3915776": 1, "3981312": 1, "4014080": 2, "4046848": 1, "4079616": 3, "4112384": 2, "4145152": 2, "4227072": 1, "4358144": 1, "4423680": 2, "4489216": 2, "4554752": 2, "4620288": 3, "4685824": 3, "4751360": 1, "4816896": 1, "4882432": 2, "4947968": 2, "5079040": 1, "5144576": 2, "5210112": 1, "5406720": 1, "5472256": 3, "5603328": 1, "5734400": 1, "5799936": 1, "5996544": 3, "6127616": 1, "6258688": 1, "6389760": 2, "6520832": 1, "6651904": 1, "6717440": 3, "6782976": 1, "6914048": 1, "7045120": 2, "7176192": 2, "7307264": 1, "7503872": 1, "7569408": 1, "7700480": 2, "7831552": 1, "7962624": 2, "8028160": 2, "8159232": 1, "8290304": 1, "8585216": 2, "8716288": 1, "8847360": 1, "8978432": 1, "9109504": 1, "9502720": 2, "9633792": 1, "9895936": 1, "10027008": 2, "10158080": 1, "10682368": 1, "10813440": 1, "11599872": 1, "11993088": 1, "12124160": 1, "12255232": 2, "12386304": 1, "12517376": 1, "12648448": 1, "12779520": 1, "13041664": 9, "14090240": 1, "15138816": 1, "15794176": 1, "16187392": 1, "42729472": 1, "45875200": 1, "103284736": 1, "135266304": 1, "143654912": 1, "162529280": 1, "173015040": 1, "200278016": 1, "204472320": 1, "208666624": 1, "221249536": 1, "229638144": 1, "256901120": 1, "283115520": 2, "291504128": 1, "304087040": 1, "308281344": 2, "312475648": 1, "325058560": 1, "354418688": 1, "367001600": 12, "375390208": 1, "387973120": 1, "396361728": 2, "400556032": 12, "480247808": 1, "513802240": 1, "530579456": 1, "566231040": 1, "591396864": 1, "608174080": 13, "633339904": 1, "683671552": 1, "692060160": 1, "708837376": 2, "725614592": 1, "775946240": 3, "792723456": 1, "809500672": 4, "817889280": 1, "843055104": 1, "868220928": 3, "901775360": 1, "910163968": 2, "918552576": 2, "926941184": 3}}, "lat_ns": {"min": 8297, "max": 929474369, "mean": 34372.489482, "stddev": 2151136.948037, "N": 6491501}, "bw_min": 296824, "bw_max": 4045936, "bw_agg": 100.0, "bw_mean": 2831241.335569, "bw_dev": 47870.61124, "bw_samples": 407, "iops_min": 74206, "iops_max": 1011484, "iops_mean": 707810.333204, "iops_stddev": 11967.659422, "iops_samples": 407}, "trim": {"io_bytes": 0, "io_kbytes": 0, "bw_bytes": 0, "bw": 0, "iops": 0.0, "runtime": 0, "total_ios": 0, "short_ios": 0, "drop_ios": 0, "slat_ns": {"min": 0, "max": 0, "mean": 0.0, "stddev": 0.0, "N": 0}, "clat_ns": {"min": 0, "max": 0, "mean": 0.0, "stddev": 0.0, "N": 0}, "lat_ns": {"min": 0, "max": 0, "mean": 0.0, "stddev": 0.0, "N": 0}, "bw_min": 0, "bw_max": 0, "bw_agg": 0.0, "bw_mean": 0.0, "bw_dev": 0.0, "bw_samples": 0, "iops_min": 0, "iops_max": 0, "iops_mean": 0.0, "iops_stddev": 0.0, "iops_samples": 0}, "sync": {"total_ios": 0, "lat_ns": {"min": 0, "max": 0, "mean": 0.0, "stddev": 0.0, "N": 0}}, "job_runtime": 230001, "usr_cpu": 3.99433, "sys_cpu": 68.966657, "ctx": 544907, "majf": 0, "minf": 1353, "iodepth_level": {"1": 100.0, "2": 0.0, "4": 0.0, "8": 0.0, "16": 0.0, "32": 0.0, ">=64": 0.0}, "iodepth_submit": {"0": 0.0, "4": 100.0, "8": 0.0, "16": 0.0, "32": 0.0, "64": 0.0, ">=64": 0.0}, "iodepth_complete": {"0": 0.0, "4": 100.0, "8": 0.0, "16": 0.0, "32": 0.0, "64": 0.0, ">=64": 0.0}, "latency_ns": {"2": 0.0, "4": 0.0, "10": 0.0, "20": 0.0, "50": 0.0, "100": 0.0, "250": 0.0, "500": 0.0, "750": 0.0, "1000": 0.0}, "latency_us": {"2": 0.0, "4": 0.0, "10": 0.051329, "20": 30.562084, "50": 64.92272, "100": 4.232719, "250": 0.216406, "500": 0.01, "750": 0.01, "1000": 0.01}, "latency_ms": {"2": 0.01, "4": 0.01, "10": 0.01, "20": 0.01, "50": 0.01, "100": 0.0, "250": 0.01, "500": 0.01, "750": 0.01, "1000": 0.01, "2000": 0.0, ">=2000": 0.0}, "latency_depth": 1, "latency_target": 0, "latency_percentile": 100.0, "latency_window": 0}]}, "cpu_time": {"allcpu": {"user": 10.139999999999418, "nice": 0.0, "system": 268.5, "idle": 516.5199999958277, "iowait": 0.009999999999990905, "irq": 0.9700000000000273, "softirq": 1.009999999999991, "steal": 0.0, "guest": 0.0, "guest_nice": 0.0}, "percpu": [{"cpu_number": 0, "user": 0.2600000000000193, "nice": 0.0, "system": 7.079999999999927, "idle": 3.640000000130385, "iowait": 0.0, "irq": 0.030000000000001137, "softirq": 0.030000000000001137, "steal": 0.0, "guest": 0.0, "guest_nice": 0.0}, {"cpu_number": 0, "user": 0.3199999999999932, "nice": 0.0, "system": 7.739999999999782, "idle": 2.909999999916181, "iowait": 0.0, "irq": 0.03000000000002956, "softirq": 0.030000000000001137, "steal": 0.0, "guest": 0.0, "guest_nice": 0.0}, {"cpu_number": 0, "user": 0.28999999999999204, "nice": 0.0, "system": 7.220000000000255, "idle": 3.540000000037253, "iowait": 0.0, "irq": 0.030000000000001137, "softirq": 0.030000000000001137, "steal": 0.0, "guest": 0.0, "guest_nice": 0.0}, {"cpu_number": 0, "user": 0.3100000000000023, "nice": 0.0, "system": 7.619999999999891, "idle": 3.0600000000558794, "iowait": 0.0, "irq": 0.030000000000001137, "softirq": 0.030000000000001137, "steal": 0.0, "guest": 0.0, "guest_nice": 0.0}, {"cpu_number": 0, "user": 0.2600000000000193, "nice": 0.0, "system": 7.010000000000218, "idle": 3.670000000158325, "iowait": 0.0, "irq": 0.030000000000001137, "softirq": 0.019999999999999574, "steal": 0.0, "guest": 0.0, "guest_nice": 0.0}, {"cpu_number": 0, "user": 0.2799999999999727, "nice": 0.0, "system": 7.4299999999993815, "idle": 3.2199999999720603, "iowait": 0.0, "irq": 0.029999999999997584, "softirq": 0.029999999999997584, "steal": 0.0, "guest": 0.0, "guest_nice": 0.0}, {"cpu_number": 0, "user": 0.3100000000000023, "nice": 0.0, "system": 7.399999999999636, "idle": 3.2199999999720603, "iowait": 0.009999999999999787, "irq": 0.029999999999997584, "softirq": 0.020000000000003126, "steal": 0.0, "guest": 0.0, "guest_nice": 0.0}, {"cpu_number": 0, "user": 0.35000000000002274, "nice": 0.0, "system": 7.9099999999998545, "idle": 2.670000000158325, "iowait": 0.0, "irq": 0.030000000000001137, "softirq": 0.020000000000003126, "steal": 0.0, "guest": 0.0, "guest_nice": 0.0}, {"cpu_number": 0, "user": 0.3299999999999841, "nice": 0.0, "system": 8.300000000000182, "idle": 2.340000000083819, "iowait": 0.0, "irq": 0.020000000000003126, "softirq": 0.020000000000003126, "steal": 0.0, "guest": 0.0, "guest_nice": 0.0}, {"cpu_number": 0, "user": 0.3100000000000023, "nice": 0.0, "system": 7.680000000000291, "idle": 2.8899999998975545, "iowait": 0.0, "irq": 0.019999999999999574, "softirq": 0.020000000000003126, "steal": 0.0, "guest": 0.0, "guest_nice": 0.0}, {"cpu_number": 0, "user": 0.22999999999996135, "nice": 0.0, "system": 7.339999999999236, "idle": 3.3500000000931323, "iowait": 0.0, "irq": 0.029999999999997584, "softirq": 0.030000000000001137, "steal": 0.0, "guest": 0.0, "guest_nice": 0.0}, {"cpu_number": 0, "user": 0.3100000000000023, "nice": 0.0, "system": 7.3799999999992, "idle": 3.25, "iowait": 0.0, "irq": 0.030000000000001137, "softirq": 0.030000000000001137, "steal": 0.0, "guest": 0.0, "guest_nice": 0.0}, {"cpu_number": 0, "user": 0.18999999999999773, "nice": 0.0, "system": 7.0600000000004, "idle": 3.6299999998882413, "iowait": 0.0, "irq": 0.030000000000001137, "softirq": 0.020000000000003126, "steal": 0.0, "guest": 0.0, "guest_nice": 0.0}, {"cpu_number": 0, "user": 0.28999999999999204, "nice": 0.0, "system": 7.6799999999993815, "idle": 3.0300000000279397, "iowait": 0.0, "irq": 0.030000000000001137, "softirq": 0.019999999999999574, "steal": 0.0, "guest": 0.0, "guest_nice": 0.0}, {"cpu_number": 0, "user": 0.36000000000001364, "nice": 0.0, "system": 7.8400000000001455, "idle": 2.75, "iowait": 0.0, "irq": 0.030000000000001137, "softirq": 0.030000000000001137, "steal": 0.0, "guest": 0.0, "guest_nice": 0.0}, {"cpu_number": 0, "user": 0.28999999999999204, "nice": 0.0, "system": 7.260000000000218, "idle": 3.3799999998882413, "iowait": 0.0, "irq": 0.030000000000001137, "softirq": 0.02999999999999403, "steal": 0.0, "guest": 0.0, "guest_nice": 0.0}, {"cpu_number": 0, "user": 0.25, "nice": 0.0, "system": 7.020000000000437, "idle": 3.669999999925494, "iowait": 0.0, "irq": 0.030000000000001137, "softirq": 0.030000000000001137, "steal": 0.0, "guest": 0.0, "guest_nice": 0.0}, {"cpu_number": 0, "user": 0.2300000000000182, "nice": 0.0, "system": 7.099999999999454, "idle": 3.550000000046566, "iowait": 0.0, "irq": 0.030000000000001137, "softirq": 0.030000000000001137, "steal": 0.0, "guest": 0.0, "guest_nice": 0.0}, {"cpu_number": 0, "user": 0.0, "nice": 0.0, "system": 0.0, "idle": 11.149999999906868, "iowait": 0.0, "irq": 0.0, "softirq": 0.0, "steal": 0.0, "guest": 0.0, "guest_nice": 0.0}, {"cpu_number": 0, "user": 0.0, "nice": 0.0, "system": 0.0, "idle": 11.139999999897555, "iowait": 0.0, "irq": 0.0, "softirq": 0.0, "steal": 0.0, "guest": 0.0, "guest_nice": 0.0}, {"cpu_number": 0, "user": 0.0, "nice": 0.0, "system": 0.0, "idle": 11.149999999906868, "iowait": 0.0, "irq": 0.0, "softirq": 0.0, "steal": 0.0, "guest": 0.0, "guest_nice": 0.0}, {"cpu_number": 0, "user": 0.0, "nice": 0.0, "system": 0.0, "idle": 11.149999999906868, "iowait": 0.0, "irq": 0.0, "softirq": 0.0, "steal": 0.0, "guest": 0.0, "guest_nice": 0.0}, {"cpu_number": 0, "user": 0.0, "nice": 0.0, "system": 0.0, "idle": 11.140000000130385, "iowait": 0.0, "irq": 0.0, "softirq": 0.0, "steal": 0.0, "guest": 0.0, "guest_nice": 0.0}, {"cpu_number": 0, "user": 0.0, "nice": 0.0, "system": 0.0, "idle": 11.149999999906868, "iowait": 0.0, "irq": 0.0, "softirq": 0.0, "steal": 0.0, "guest": 0.0, "guest_nice": 0.0}, {"cpu_number": 0, "user": 0.0, "nice": 0.0, "system": 0.0, "idle": 11.150000000139698, "iowait": 0.0, "irq": 0.0, "softirq": 0.0, "steal": 0.0, "guest": 0.0, "guest_nice": 0.0}, {"cpu_number": 0, "user": 0.0, "nice": 0.0, "system": 0.0, "idle": 11.140000000130385, "iowait": 0.0, "irq": 0.0, "softirq": 0.0, "steal": 0.0, "guest": 0.0, "guest_nice": 0.0}, {"cpu_number": 0, "user": 0.0, "nice": 0.0, "system": 0.0, "idle": 11.150000000139698, "iowait": 0.0, "irq": 0.0, "softirq": 0.0, "steal": 0.0, "guest": 0.0, "guest_nice": 0.0}, {"cpu_number": 0, "user": 0.0, "nice": 0.0, "system": 0.0, "idle": 11.149999999906868, "iowait": 0.0, "irq": 0.0, "softirq": 0.0, "steal": 0.0, "guest": 0.0, "guest_nice": 0.0}, {"cpu_number": 0, "user": 0.0, "nice": 0.0, "system": 0.0, "idle": 11.150000000139698, "iowait": 0.0, "irq": 0.0, "softirq": 0.0, "steal": 0.0, "guest": 0.0, "guest_nice": 0.0}, {"cpu_number": 0, "user": 0.0, "nice": 0.0, "system": 0.0, "idle": 11.149999999906868, "iowait": 0.0, "irq": 0.0, "softirq": 0.0, "steal": 0.0, "guest": 0.0, "guest_nice": 0.0}, {"cpu_number": 0, "user": 0.0, "nice": 0.0, "system": 0.0, "idle": 11.149999999906868, "iowait": 0.0, "irq": 0.0, "softirq": 0.0, "steal": 0.0, "guest": 0.0, "guest_nice": 0.0}, {"cpu_number": 0, "user": 0.0, "nice": 0.0, "system": 0.0, "idle": 11.149999999906868, "iowait": 0.0, "irq": 0.0, "softirq": 0.0, "steal": 0.0, "guest": 0.0, "guest_nice": 0.0}, {"cpu_number": 0, "user": 0.0, "nice": 0.0, "system": 0.0, "idle": 11.150000000139698, "iowait": 0.0, "irq": 0.0, "softirq": 0.0, "steal": 0.0, "guest": 0.0, "guest_nice": 0.0}, {"cpu_number": 0, "user": 0.0, "nice": 0.0, "system": 0.0, "idle": 11.140000000130385, "iowait": 0.0, "irq": 0.0, "softirq": 0.0, "steal": 0.0, "guest": 0.0, "guest_nice": 0.0}, {"cpu_number": 0, "user": 0.0, "nice": 0.0, "system": 0.0, "idle": 11.150000000139698, "iowait": 0.0, "irq": 0.0, "softirq": 0.0, "steal": 0.0, "guest": 0.0, "guest_nice": 0.0}, {"cpu_number": 0, "user": 0.0, "nice": 0.0, "system": 0.0, "idle": 11.149999999906868, "iowait": 0.0, "irq": 0.0, "softirq": 0.0, "steal": 0.0, "guest": 0.0, "guest_nice": 0.0}, {"cpu_number": 0, "user": 0.27000000000001023, "nice": 0.0, "system": 7.559999999999491, "idle": 3.0999999998603016, "iowait": 0.0, "irq": 0.030000000000001137, "softirq": 0.030000000000001137, "steal": 0.0, "guest": 0.0, "guest_nice": 0.0}, {"cpu_number": 0, "user": 0.2400000000000091, "nice": 0.0, "system": 7.329999999999927, "idle": 3.380000000121072, "iowait": 0.0, "irq": 0.019999999999999574, "softirq": 0.030000000000001137, "steal": 0.0, "guest": 0.0, "guest_nice": 0.0}, {"cpu_number": 0, "user": 0.18999999999999773, "nice": 0.0, "system": 6.910000000000764, "idle": 3.75, "iowait": 0.0, "irq": 0.030000000000001137, "softirq": 0.0400000000000027, "steal": 0.0, "guest": 0.0, "guest_nice": 0.0}, {"cpu_number": 0, "user": 0.2699999999999818, "nice": 0.0, "system": 7.130000000000109, "idle": 3.4799999999813735, "iowait": 0.010000000000005116, "irq": 0.020000000000003126, "softirq": 0.030000000000001137, "steal": 0.0, "guest": 0.0, "guest_nice": 0.0}, {"cpu_number": 0, "user": 0.2300000000000182, "nice": 0.0, "system": 7.430000000000291, "idle": 3.2399999999906868, "iowait": 0.0, "irq": 0.029999999999997584, "softirq": 0.030000000000001137, "steal": 0.0, "guest": 0.0, "guest_nice": 0.0}, {"cpu_number": 0, "user": 0.22000000000002728, "nice": 0.0, "system": 7.510000000000218, "idle": 3.230000000214204, "iowait": 0.0, "irq": 0.030000000000001137, "softirq": 0.030000000000001137, "steal": 0.0, "guest": 0.0, "guest_nice": 0.0}, {"cpu_number": 0, "user": 0.3299999999999841, "nice": 0.0, "system": 7.5, "idle": 3.1100000001024455, "iowait": 0.0, "irq": 0.030000000000001137, "softirq": 0.01999999999999602, "steal": 0.0, "guest": 0.0, "guest_nice": 0.0}, {"cpu_number": 0, "user": 0.3499999999999659, "nice": 0.0, "system": 7.930000000000291, "idle": 2.6900000001769513, "iowait": 0.0, "irq": 0.030000000000001137, "softirq": 0.030000000000001137, "steal": 0.0, "guest": 0.0, "guest_nice": 0.0}, {"cpu_number": 0, "user": 0.2599999999999909, "nice": 0.0, "system": 7.329999999999927, "idle": 3.300000000046566, "iowait": 0.0, "irq": 0.02999999999999403, "softirq": 0.02999999999999403, "steal": 0.0, "guest": 0.0, "guest_nice": 0.0}, {"cpu_number": 0, "user": 0.3299999999999841, "nice": 0.0, "system": 7.550000000000182, "idle": 3.050000000046566, "iowait": 0.0, "irq": 0.030000000000001137, "softirq": 0.030000000000001137, "steal": 0.0, "guest": 0.0, "guest_nice": 0.0}, {"cpu_number": 0, "user": 0.2599999999999909, "nice": 0.0, "system": 7.359999999999673, "idle": 3.3100000000558794, "iowait": 0.0, "irq": 0.019999999999999574, "softirq": 0.029999999999997584, "steal": 0.0, "guest": 0.0, "guest_nice": 0.0}, {"cpu_number": 0, "user": 0.25, "nice": 0.0, "system": 7.460000000000036, "idle": 3.2399999999906868, "iowait": 0.0, "irq": 0.030000000000001137, "softirq": 0.030000000000001137, "steal": 0.0, "guest": 0.0, "guest_nice": 0.0}, {"cpu_number": 0, "user": 0.2699999999999818, "nice": 0.0, "system": 7.819999999999709, "idle": 2.8499999998603016, "iowait": 0.0, "irq": 0.029999999999997584, "softirq": 0.030000000000001137, "steal": 0.0, "guest": 0.0, "guest_nice": 0.0}, {"cpu_number": 0, "user": 0.29000000000002046, "nice": 0.0, "system": 7.75, "idle": 2.909999999916181, "iowait": 0.0, "irq": 0.030000000000001137, "softirq": 0.030000000000001137, "steal": 0.0, "guest": 0.0, "guest_nice": 0.0}, {"cpu_number": 0, "user": 0.3400000000000034, "nice": 0.0, "system": 7.739999999999782, "idle": 2.880000000121072, "iowait": 0.0, "irq": 0.030000000000001137, "softirq": 0.030000000000001137, "steal": 0.0, "guest": 0.0, "guest_nice": 0.0}, {"cpu_number": 0, "user": 0.3100000000000023, "nice": 0.0, "system": 7.520000000000437, "idle": 3.090000000083819, "iowait": 0.0, "irq": 0.019999999999999574, "softirq": 0.030000000000001137, "steal": 0.0, "guest": 0.0, "guest_nice": 0.0}, {"cpu_number": 0, "user": 0.25, "nice": 0.0, "system": 6.890000000000327, "idle": 3.830000000074506, "iowait": 0.0, "irq": 0.01999999999999602, "softirq": 0.030000000000001137, "steal": 0.0, "guest": 0.0, "guest_nice": 0.0}, {"cpu_number": 0, "user": 0.3199999999999932, "nice": 0.0, "system": 7.720000000000255, "idle": 3.0200000000186265, "iowait": 0.0, "irq": 0.030000000000001137, "softirq": 0.02999999999999403, "steal": 0.0, "guest": 0.0, "guest_nice": 0.0}, {"cpu_number": 0, "user": 0.0, "nice": 0.0, "system": 0.0, "idle": 11.149999999906868, "iowait": 0.0, "irq": 0.0, "softirq": 0.0, "steal": 0.0, "guest": 0.0, "guest_nice": 0.0}, {"cpu_number": 0, "user": 0.0, "nice": 0.0, "system": 0.0, "idle": 11.149999999906868, "iowait": 0.0, "irq": 0.0, "softirq": 0.0, "steal": 0.0, "guest": 0.0, "guest_nice": 0.0}, {"cpu_number": 0, "user": 0.0, "nice": 0.0, "system": 0.0, "idle": 11.150000000139698, "iowait": 0.0, "irq": 0.0, "softirq": 0.0, "steal": 0.0, "guest": 0.0, "guest_nice": 0.0}, {"cpu_number": 0, "user": 0.0, "nice": 0.0, "system": 0.0, "idle": 11.149999999906868, "iowait": 0.0, "irq": 0.0, "softirq": 0.0, "steal": 0.0, "guest": 0.0, "guest_nice": 0.0}, {"cpu_number": 0, "user": 0.0, "nice": 0.0, "system": 0.0, "idle": 11.149999999906868, "iowait": 0.0, "irq": 0.0, "softirq": 0.0, "steal": 0.0, "guest": 0.0, "guest_nice": 0.0}, {"cpu_number": 0, "user": 0.0, "nice": 0.0, "system": 0.0, "idle": 11.149999999906868, "iowait": 0.0, "irq": 0.0, "softirq": 0.0, "steal": 0.0, "guest": 0.0, "guest_nice": 0.0}, {"cpu_number": 0, "user": 0.0, "nice": 0.0, "system": 0.0, "idle": 11.150000000139698, "iowait": 0.0, "irq": 0.0, "softirq": 0.0, "steal": 0.0, "guest": 0.0, "guest_nice": 0.0}, {"cpu_number": 0, "user": 0.0, "nice": 0.0, "system": 0.0, "idle": 11.150000000139698, "iowait": 0.0, "irq": 0.0, "softirq": 0.0, "steal": 0.0, "guest": 0.0, "guest_nice": 0.0}, {"cpu_number": 0, "user": 0.0, "nice": 0.0, "system": 0.0, "idle": 11.150000000139698, "iowait": 0.0, "irq": 0.0, "softirq": 0.0, "steal": 0.0, "guest": 0.0, "guest_nice": 0.0}, {"cpu_number": 0, "user": 0.0, "nice": 0.0, "system": 0.0, "idle": 11.150000000139698, "iowait": 0.0, "irq": 0.0, "softirq": 0.0, "steal": 0.0, "guest": 0.0, "guest_nice": 0.0}, {"cpu_number": 0, "user": 0.0, "nice": 0.0, "system": 0.0, "idle": 11.139999999897555, "iowait": 0.0, "irq": 0.0, "softirq": 0.0, "steal": 0.0, "guest": 0.0, "guest_nice": 0.0}, {"cpu_number": 0, "user": 0.0, "nice": 0.0, "system": 0.0, "idle": 11.149999999906868, "iowait": 0.0, "irq": 0.0, "softirq": 0.0, "steal": 0.0, "guest": 0.0, "guest_nice": 0.0}, {"cpu_number": 0, "user": 0.0, "nice": 0.0, "system": 0.0, "idle": 11.149999999906868, "iowait": 0.0, "irq": 0.0, "softirq": 0.0, "steal": 0.0, "guest": 0.0, "guest_nice": 0.0}, {"cpu_number": 0, "user": 0.0, "nice": 0.0, "system": 0.0, "idle": 11.150000000139698, "iowait": 0.0, "irq": 0.0, "softirq": 0.0, "steal": 0.0, "guest": 0.0, "guest_nice": 0.0}, {"cpu_number": 0, "user": 0.0, "nice": 0.0, "system": 0.0, "idle": 11.139999999897555, "iowait": 0.0, "irq": 0.0, "softirq": 0.0, "steal": 0.0, "guest": 0.0, "guest_nice": 0.0}, {"cpu_number": 0, "user": 0.0, "nice": 0.0, "system": 0.0, "idle": 11.150000000139698, "iowait": 0.0, "irq": 0.0, "softirq": 0.0, "steal": 0.0, "guest": 0.0, "guest_nice": 0.0}, {"cpu_number": 0, "user": 0.0, "nice": 0.0, "system": 0.0, "idle": 11.149999999906868, "iowait": 0.0, "irq": 0.0, "softirq": 0.0, "steal": 0.0, "guest": 0.0, "guest_nice": 0.0}, {"cpu_number": 0, "user": 0.0, "nice": 0.0, "system": 0.0, "idle": 11.149999999906868, "iowait": 0.0, "irq": 0.0, "softirq": 0.0, "steal": 0.0, "guest": 0.0, "guest_nice": 0.0}]}, "itxg_bypass_stats": {"assign__write_upgrade": 0, "assign__downgrade": 0, "assign__aquisition_total": 0, "assign__vtable": 0, "assign__exit": 0, "assign__total": 0, "commit__total": 0, "commit__aquire": 0}, "zvol_stats": {"submit_bio__zvol_write(count)": 0, "submit_bio__zvol_write(with_taskq_if_enabled)": 0, "zvol_write__taskq_qdelay": 0, "zvol_write__1zil_commit": 0, "zvol_write__rangelock_enter": 0, "zvol_write__hold_write_by_dnode": 0, "zvol_write__zvol_log_write_finish": 0, "zvol_write__bio_end_io": 0, "zvol_write__2zil_commit": 0}, "zil_pmem_stats": {"write_entry_time": 96572050425, "write_entry_count": 7446166, "get_data_time": 0, "get_data_count": 0}, "zil_pmem_ringbuf_stats": {"prb_write__get_committer_slot": 34573402267, "prb_write__put_committer_slot": 4502647731, "prb_write__dt_sl_aquisition": 317927519, "prb_write__dt_sl_held": 667586211, "prb_write__pmem": 52783682496, "prb_write__committerslothist_b_other": 0, "prb_write__committerslothist_b_0": 1989080, "prb_write__committerslothist_b_1": 1677874, "prb_write__committerslothist_b_2": 1292759, "prb_write__committerslothist_b_3": 883494, "prb_write__committerslothist_b_4": 549204, "prb_write__committerslothist_b_5": 277255, "prb_write__committerslothist_b_6": 185395, "prb_write__committerslothist_b_7": 166344, "prb_write__committerslothist_b_8": 141136, "prb_write__committerslothist_b_9": 113640, "prb_write__committerslothist_b_10": 84455, "prb_write__committerslothist_b_11": 84994, "prb_write__committerslothist_b_12": 0, "prb_write__committerslothist_b_13": 0, "prb_write__committerslothist_b_14": 0, "prb_write__committerslothist_b_15": 0, "prb_write__committerslothist_b_16": 0, "prb_write__committerslothist_b_17": 0, "prb_write__committerslothist_b_18": 0, "prb_write__committerslothist_b_19": 0, "prb_write__committerslothist_b_20": 0, "prb_write__committerslothist_b_21": 0, "prb_write__committerslothist_b_22": 0, "prb_write__committerslothist_b_23": 0, "prb_write__committerslothist_b_24": 0}}